opticalflow3D/__init__.py
opticalflow3D/opticalflow3D.py
opticalflow3D/helpers/__init__.py
opticalflow3D/helpers/farneback_functions.py
opticalflow3D/helpers/helpers.py
opticalflow3D/helpers/pyrlk_functions.py
opticalflow3d-0.3.2.dist-info/METADATA
opticalflow3d-0.3.2.dist-info/WHEEL
opticalflow3d-0.3.2.dist-info/top_level.txt
opticalflow3d-0.3.2.dist-info/RECORD
