Metadata-Version: 2.1
Name: opticalflow3d
Version: 0.3.2
Summary: GPU/CUDA optimized implementation of 3D optical flow algorithms such as Farneback two frame motion estimation and Lucas Kanade dense optical flow algorithms
Home-page: https://gitlab.com/xianbin.yong13/opticalflow3d
Author: Xianbin Yong
Author-email: xianbin.yong13@sps.nus.edu.sg
License: GPLv3
Project-URL: Research group, https://ctlimlab.org/
Project-URL: Source, https://gitlab.com/xianbin.yong13/opticalflow3d
Classifier: Intended Audience :: Science/Research
Classifier: Programming Language :: Python
Classifier: Programming Language :: Python :: 3
Classifier: Programming Language :: Python :: 3 :: Only
Classifier: Programming Language :: Python :: 3.7
Classifier: Programming Language :: Python :: 3.8
Classifier: Programming Language :: Python :: 3.9
Classifier: License :: OSI Approved :: GNU General Public License v3 (GPLv3)
Classifier: Operating System :: OS Independent
Classifier: Development Status :: 3 - Alpha
Classifier: Topic :: Scientific/Engineering
Requires-Python: >=3.7
Requires-Dist: numpy (>=1.17.0)
Requires-Dist: numba (>=0.47.0)
Requires-Dist: scikit-image (>=0.17.1)
Requires-Dist: scipy (>=1.6.3)
Requires-Dist: tqdm (>=4.50.0)
Requires-Dist: cupy-cuda113 (>=10.0.0)
